libmedaka.abi3.so
medaka-2.2.0.data/scripts/medaka_consensus
medaka-2.2.0.data/scripts/mini_align
medaka-2.2.0.data/scripts/medaka_variant
medaka-2.2.0.data/scripts/medaka_consensus_joint
medaka-2.2.0.dist-info/RECORD
medaka-2.2.0.dist-info/WHEEL
medaka-2.2.0.dist-info/entry_points.txt
medaka-2.2.0.dist-info/top_level.txt
medaka-2.2.0.dist-info/METADATA
medaka-2.2.0.dist-info/licenses/LICENSE
medaka/options.py
medaka/vcf.py
medaka/labels.py
medaka/align.py
medaka/models.py
medaka/__init__.py
medaka/features.py
medaka/prediction.py
medaka/rle.py
medaka/medaka.py
medaka/common.py
medaka/torch_ext.py
medaka/stitch.py
medaka/smolecule.py
medaka/variant.py
medaka/datastore.py
medaka/training.py
medaka/executor.py
medaka/medaka_counts.py
medaka/architectures/base_classes.py
medaka/architectures/__init__.py
medaka/architectures/latent_space_lstm.py
medaka/architectures/read_level_modules.py
medaka/architectures/gru.py
medaka/architectures/majority_vote_model.py
medaka/.dylibs/libcrypto.3.dylib
medaka/tandem/tandem.py
medaka/tandem/alignment.py
medaka/tandem/consensus_generator.py
medaka/tandem/io.py
medaka/tandem/polisher.py
medaka/tandem/__init__.py
medaka/tandem/record_name.py
medaka/tandem/spanning_read_clusterer.py
medaka/data/r1041_e82_400bps_sup_v5.2.0_model_pt.tar.gz
medaka/data/r1041_e82_400bps_hac_v5.2.0_model_pt.tar.gz
medaka/data/r1041_e82_400bps_sup_variant_v5.0.0_model_pt.tar.gz
medaka/data/r1041_e82_400bps_hac_variant_v5.0.0_model_pt.tar.gz
