Metadata-Version: 2.4
Name: medaka
Version: 2.2.0
Summary: Neural network sequence error correction.
Home-page: https://github.com/nanoporetech/medaka
Author: ont-research
Requires-Python: >=3.10,<3.14
License-File: LICENSE
Requires-Dist: cffi
Requires-Dist: edlib
Requires-Dist: h5py
Requires-Dist: intervaltree
Requires-Dist: numpy>=2.0
Requires-Dist: ont-mappy
Requires-Dist: ont_fast5_api
Requires-Dist: ont-parasail
Requires-Dist: packaging
Requires-Dist: pysam<=0.23.0,>=0.16.0.1
Requires-Dist: pyspoa>=0.2.1
Requires-Dist: requests
Requires-Dist: tensordict
Requires-Dist: toml
Requires-Dist: torch~=2.9
Requires-Dist: tqdm
Requires-Dist: wurlitzer
Provides-Extra: abpoa
Requires-Dist: pyabpoa==1.5.1; extra == "abpoa"
Dynamic: author
Dynamic: description
Dynamic: description-content-type
Dynamic: home-page
Dynamic: license-file
Dynamic: provides-extra
Dynamic: requires-dist
Dynamic: requires-python
Dynamic: summary
